greet/__init__.py
greet/__version.py
greet/cli.py
greet_poetry-0.1.0.dev0.dist-info/entry_points.txt
greet_poetry-0.1.0.dev0.dist-info/LICENSE.md
greet_poetry-0.1.0.dev0.dist-info/METADATA
greet_poetry-0.1.0.dev0.dist-info/WHEEL
greet_poetry-0.1.0.dev0.dist-info/RECORD
