Metadata-Version: 2.3
Name: greet-poetry
Version: 0.1.0.dev0
Summary: This is a Python package template using Poetry.
License: MIT
Author: Quynh Nguyen
Author-email: <seriquynh@gmail.com>
Requires-Python: >=3.11,<4.0
Classifier: License :: OSI Approved :: MIT License
Classifier: Programming Language :: Python :: 3
Classifier: Programming Language :: Python :: 3.11
Classifier: Programming Language :: Python :: 3.12
Classifier: Programming Language :: Python :: 3.13
